[{"Ident":"1","Date":"2023-03-30T17:10:21.0632838+01:00","Complete":true,"Responses":[{"Ident":"1","Data":[{"Value":"1"},{"Value":"2"},{"Value":"3"},{"Value":"4"}]},{"Ident":"2","Data":[{"Value":"1"},{"Value":"3"},{"Value":"4"}]}]},{"Ident":"2","Date":"2023-03-30T17:10:54.1879238+01:00","Complete":true,"Responses":[{"Ident":"1","Data":[{"Value":"1"},{"Value":"4"},{"Value":"5"}]},{"Ident":"2","Data":[{"Value":"4"},{"Value":"5"}]}]},{"Ident":"3","Date":"2023-03-30T17:10:54.188399+01:00","Complete":true,"Responses":[{"Ident":"1","Data":[{"Value":"1"},{"Value":"2"},{"Value":"3"},{"Value":"4"},{"Value":"5"}]},{"Ident":"2","Data":[{"Value":"1"},{"Value":"2"},{"Value":"3"},{"Value":"4"},{"Value":"5"}]}]},{"Ident":"4","Date":"2023-03-30T17:10:54.1897265+01:00","Complete":true,"Responses":[{"Ident":"1","Data":[{"Value":"2"},{"Value":"3"},{"Value":"4"},{"Value":"5"}]},{"Ident":"2","Data":[{"Value":"2"},{"Value":"3"},{"Value":"4"},{"Value":"5"}]}]},{"Ident":"5","Date":"2023-03-30T17:10:54.1899917+01:00","Complete":true,"Responses":[{"Ident":"1","Data":[{"Value":"2"},{"Value":"4"},{"Value":"5"}]},{"Ident":"2","Data":[{"Value":"2"},{"Value":"4"},{"Value":"5"}]}]},{"Ident":"6","Date":"2023-03-30T17:10:54.1901169+01:00","Complete":true,"Responses":[{"Ident":"1","Data":[{"Value":"3"},{"Value":"4"},{"Value":"5"}]},{"Ident":"2","Data":[{"Value":"3"},{"Value":"4"}]}]},{"Ident":"7","Date":"2023-03-30T17:10:54.1902677+01:00","Complete":true,"Responses":[{"Ident":"1","Data":[{"Value":"2"},{"Value":"3"},{"Value":"4"},{"Value":"5"}]},{"Ident":"2","Data":[{"Value":"3"},{"Value":"5"}]}]},{"Ident":"8","Date":"2023-03-30T17:10:54.1904882+01:00","Complete":true,"Responses":[{"Ident":"1","Data":[{"Value":"1"},{"Value":"2"},{"Value":"3"},{"Value":"4"},{"Value":"5"}]},{"Ident":"2","Data":[{"Value":"1"},{"Value":"2"},{"Value":"3"},{"Value":"4"},{"Value":"5"}]}]},{"Ident":"9","Date":"2023-03-30T17:10:54.190602+01:00","Complete":true,"Responses":[{"Ident":"1","Data":[{"Value":"1"},{"Value":"2"},{"Value":"3"},{"Value":"4"},{"Value":"5"}]},{"Ident":"2","Data":[{"Value":"1"},{"Value":"3"},{"Value":"4"},{"Value":"5"}]}]},{"Ident":"10","Date":"2023-03-30T17:10:54.1906879+01:00","Complete":true,"Responses":[{"Ident":"1","Data":[{"Value":"1"},{"Value":"2"},{"Value":"3"},{"Value":"5"}]},{"Ident":"2","Data":[{"Value":"1"},{"Value":"2"},{"Value":"5"}]}]}]